LICENCE
MANIFEST.in
README.rst
setup.py
adworks/__init__.py
adworks/admin.py
adworks/models.py
adworks/urls.py
adworks/views.py
adworks/fixtures/test.json
adworks/static/js/swfobject.js
adworks/templates/404.html
adworks/templates/500.hmtl
adworks/templates/base.html
adworks/templates/adworks/banner_detail.html
adworks/templates/adworks/base.html
adworks/templates/adworks/campaign_detail.html
adworks/templates/adworks/client_detail.html
adworks/tests/__init__.py
adworks/tests/models.py
adworks/tests/views.py
django_adworks.egg-info/PKG-INFO
django_adworks.egg-info/SOURCES.txt
django_adworks.egg-info/dependency_links.txt
django_adworks.egg-info/not-zip-safe
django_adworks.egg-info/requires.txt
django_adworks.egg-info/top_level.txt