Metadata-Version: 1.0
Name: django-adworks
Version: 0.1
Summary: A simple Django application to manage ad banner design and approval processes.
Home-page: http://github.com/ozgurgunes/django-adworks/
Author: Ozgur Gunes
Author-email: o.gunes@gmail.com
License: UNKNOWN
Keywords: django,ad,banner,demo
Platform: UNKNOWN
Classifier: Development Status :: 4 - Beta
Classifier: Environment :: Web Environment
Classifier: Intended Audience :: Developers
Classifier: License :: OSI Approved :: MIT License
Classifier: Operating System :: OS Independent
Classifier: Programming Language :: Python
Classifier: Framework :: Django
